chandassu/telugu/__intit__.py
chandassu/telugu/check_lakshanam.py
chandassu/telugu/ganam.py
chandassu/telugu/laghuvu_guruvu.py
chandassu/telugu/nidhi.py
chandassu/telugu/padya_bhedam.py
chandassu/telugu/padyam_config.py
chandassu/telugu/panimuttu.py
chandassu/telugu/varnamala.py
chandassu-2.0.0.dist-info/LICENSE
chandassu-2.0.0.dist-info/METADATA
chandassu-2.0.0.dist-info/WHEEL
chandassu-2.0.0.dist-info/RECORD
