Metadata-Version: 2.3
Name: chandassu
Version: 2.0.0
Summary: First-ever Python library implementing 'Chandassu', metrical poetry in Global language(s)
License: MIT
Keywords: telugu,poetry,chandassu,prosody,nlp,natural-language-processing,computational-linguistics,indian-languages,metrical-analysis,cultural-preservation
Author: Boddu Sri Pavan
Author-email: boddusripavan111@gmail.com
Requires-Python: >=3.11
Classifier: Development Status :: 4 - Beta
Classifier: Intended Audience :: Developers
Classifier: Intended Audience :: Education
Classifier: Intended Audience :: Science/Research
Classifier: Topic :: Scientific/Engineering :: Artificial Intelligence
Classifier: Topic :: Text Processing :: Linguistic
Classifier: Topic :: Software Development :: Libraries :: Python Modules
Classifier: License :: OSI Approved :: MIT License
Classifier: Programming Language :: Python :: 3
Classifier: Programming Language :: Python :: 3.11
Classifier: Programming Language :: Python :: 3.12
Classifier: Programming Language :: Python :: 3.13
Classifier: Natural Language :: English
Classifier: Natural Language :: Telugu
Classifier: Operating System :: OS Independent
Project-URL: Changelog, https://github.com/BodduSriPavan-111/chandassu/releases
Project-URL: Documentation, https://chandassu-documentation.vercel.app/
Project-URL: Homepage, https://github.com/BodduSriPavan-111/chandassu
Project-URL: Issue Tracker, https://github.com/BodduSriPavan-111/chandassu/issues
Project-URL: Repository, https://github.com/BodduSriPavan-111/chandassu
Project-URL: Research Paper, https://arxiv.org/abs/2510.01233
